Products.BibfolderFlexibleView-0.4.2.2-nspkg.pth
Products.BibfolderFlexibleView-0.4.2.2.dist-info/WHEEL
Products.BibfolderFlexibleView-0.4.2.2.dist-info/metadata.json
Products.BibfolderFlexibleView-0.4.2.2.dist-info/RECORD
Products.BibfolderFlexibleView-0.4.2.2.dist-info/top_level.txt
Products.BibfolderFlexibleView-0.4.2.2.dist-info/DESCRIPTION.rst
Products.BibfolderFlexibleView-0.4.2.2.dist-info/namespace_packages.txt
Products.BibfolderFlexibleView-0.4.2.2.dist-info/METADATA
Products.BibfolderFlexibleView-0.4.2.2.dist-info/entry_points.txt
Products/BibfolderFlexibleView/__init__.py
Products/BibfolderFlexibleView/config.py
Products/BibfolderFlexibleView/tool/flexview_tool.py
Products/BibfolderFlexibleView/tool/__init__.py
Products/BibfolderFlexibleView/tool/safe_eval.py
