Metadata-Version: 2.0
Name: Products.BibfolderFlexibleView
Version: 0.4.2.2
Summary: Flexible folder views for CMFBibliographyAT
Home-page: http://pypi.python.org/pypi/Products.BibfolderFlexibleView
Author: Andreas Jung
Author-email: info@zopyx.com
License: GPL
Keywords: web application server zope zope2 cmf plone bibliography
Platform: UNKNOWN
Classifier: Framework :: Plone
Classifier: Framework :: Zope2
Classifier: Framework :: Zope3
Classifier: Programming Language :: Python
Classifier: Topic :: Software Development :: Libraries :: Python Modules
Requires-Dist: setuptools
Requires-Dist: Products.CMFBibliographyAT
